{
  "generated_at": "2026-05-05T01:19:28.112013+00:00",
  "model": "nvidia/nemotron-3-super-120b-a12b:free",
  "news": [
    {
      "category": "STILL MINTING",
      "headline": "STILL MINTING",
      "summary": "Current card is still minting. \"Just Culture\" by JamesAndrew \u2014 50.5M TDH from 103 voters. Top supporter: gpebbles (12.8M TDH).",
      "source": "The Memes",
      "link": "https://6529.io/the-memes",
      "image": {
        "url": "https://d3lqz0a4bldqgf.cloudfront.net/images/original/0x33FD426905F149f8376e227d0C9D3340AaD17aF1/491.PNG",
        "label": "Just Culture - JamesAndrew",
        "type": "image"
      },
      "dataBoxes": null
    },
    {
      "category": "MINTING WEDNESDAY",
      "headline": "Minting Wednesday",
      "summary": " \"Pursuit of Volatility\" by Strauss \u2014 61.2M TDH from 96 voters. Top supporter: Giopetto (7.0M TDH).",
      "source": "The Memes",
      "link": "https://6529.io/the-memes",
      "image": {
        "url": "https://d3lqz0a4bldqgf.cloudfront.net/drops/author_1c914f7f-fae0-4314-8792-84fe956acea0/0450d053-06e1-4a69-9fe8-ca99554942c6.gif",
        "label": "Pursuit of Volatility - Strauss",
        "type": "image"
      },
      "dataBoxes": null
    },
    {
      "category": "TOP MEMES",
      "headline": "6529er Leads with 92.9M Projected TDH",
      "summary": "\"Keys and Gates\" by 6529er (92.9M projected TDH, 101 voters) | \"EMERGENT\" by AEZY (39.3M projected TDH, 63 voters) | \"Network State of Mind\" by Zigmarillion (30.2M projected TDH, 70 voters) Next selection: Wed May 06 at 17:00 CET.",
      "source": "The Memes - Main Stage",
      "link": "https://6529.io/waves/b6128077-ea78-4dd9-b381-52c4eadb2077",
      "image": {
        "url": "https://d3lqz0a4bldqgf.cloudfront.net/drops/author_0f82d54d-87b4-11ee-9d82-029a0e4b6159/30fc94f8-96a7-4a88-be49-2443eb117dbe/Keys-and-Gates.jpg",
        "label": "Keys and Gates - 6529er",
        "type": "image"
      },
      "dataBoxes": [
        {
          "label": "6529er",
          "value": "92.9M",
          "sub": "proj. (101 votes)"
        },
        {
          "label": "AEZY",
          "value": "39.3M",
          "sub": "proj. (63 votes)"
        },
        {
          "label": "Zigmarillion",
          "value": "30.2M",
          "sub": "proj. (70 votes)"
        }
      ]
    },
    {
      "category": "NEW MEMES SUBMISSIONS",
      "headline": "4 New Memes Submissions This Week",
      "summary": "4 submissions this week. Ranking: CasaNUA (5.5M) | Sert (2.6M) | grubnot (1.7M) | MintFace (806K).",
      "source": "Main Stage",
      "link": "https://6529.io/waves/b6128077-ea78-4dd9-b381-52c4eadb2077",
      "image": {
        "url": "https://d3lqz0a4bldqgf.cloudfront.net/drops/author_0f8306a5-87b4-11ee-9d82-029a0e4b6159/186e691f-09f8-4a05-806f-891a1aa29185/6529-Memes-at-the-Boys-Club-Hugo-Faz-and-Pate-4K.mp4",
        "label": "CasaNUA (5.5M)",
        "type": "video"
      },
      "images": [
        {
          "url": "https://d3lqz0a4bldqgf.cloudfront.net/drops/author_0f8306a5-87b4-11ee-9d82-029a0e4b6159/186e691f-09f8-4a05-806f-891a1aa29185/6529-Memes-at-the-Boys-Club-Hugo-Faz-and-Pate-4K.mp4",
          "label": "CasaNUA (5.5M)",
          "type": "video"
        },
        {
          "url": "https://d3lqz0a4bldqgf.cloudfront.net/drops/author_6e9211c7-8365-43f8-8a48-6becfa42b017/f6cb90e2-f1f4-4ef0-942d-32faa785d086/I-seize-mymemes.jpg",
          "label": "grubnot (1.7M)",
          "type": "image"
        }
      ],
      "dataBoxes": null
    },
    {
      "category": "TOP SUPERRARE",
      "headline": "JasonOPhoto Leads with 2.8M TDH",
      "summary": "JasonOPhoto (2.8M) | Articulate (2.2M) | Zigmarillion (1.2M) | Kostas_Photo (765K) | awhurst (555K) | blake69 (322K) | Gsen (149K) | Bicasso (2K)",
      "source": "SuperRare x 6529",
      "link": "https://6529.io/waves/d22e3046-a00e-48b9-b245-a339a44c37cd",
      "image": {
        "url": "https://d3lqz0a4bldqgf.cloudfront.net/drops/author_746dccd5-fdc4-4243-a54d-c981ff5ba461/31b825aa-23bc-47f0-ab89-cd850a4d94d8.jpg",
        "label": "JasonOPhoto (2.8M)",
        "type": "image"
      }
    },
    {
      "category": "SALES RECAP",
      "headline": "30 Sales Today - 1.74 ETH Volume",
      "summary": "30 sales in 24h for 1.74 ETH. Highest: \"Meme BUIDLoors\" at 0.270 ETH.",
      "source": "OpenSea",
      "link": "https://opensea.io/collection/thememes6529",
      "image": {
        "url": "https://d3lqz0a4bldqgf.cloudfront.net/images/scaled_x450/0x33FD426905F149f8376e227d0C9D3340AaD17aF1/262.WEBP",
        "label": "Meme BUIDLoors - 0.270 ETH",
        "type": "image"
      },
      "images": [
        {
          "url": "https://d3lqz0a4bldqgf.cloudfront.net/images/scaled_x450/0x33FD426905F149f8376e227d0C9D3340AaD17aF1/262.WEBP",
          "label": "Meme BUIDLoors - 0.270 ETH",
          "type": "image"
        },
        {
          "url": "https://d3lqz0a4bldqgf.cloudfront.net/images/scaled_x450/0x33FD426905F149f8376e227d0C9D3340AaD17aF1/339.GIF",
          "label": "Powered by Time - 0.100 ETH",
          "type": "image"
        },
        {
          "url": "https://d3lqz0a4bldqgf.cloudfront.net/images/scaled_x450/0x33FD426905F149f8376e227d0C9D3340AaD17aF1/187.WEBP",
          "label": "Meme Enjoyoor - 0.099 ETH",
          "type": "image"
        }
      ],
      "dataBoxes": [
        {
          "label": "Sales 24h",
          "value": "30",
          "sub": ""
        },
        {
          "label": "Volume 24h",
          "value": "1.74",
          "sub": "ETH"
        },
        {
          "label": "Top Sale",
          "value": "0.270",
          "sub": "Meme BUIDLoors"
        },
        {
          "label": "Floor",
          "value": "0.01621998",
          "sub": "ETH"
        }
      ]
    }
  ],
  "ticker": [
    {
      "label": "24h Vol",
      "value": "1.74 ETH",
      "raw": 1.7367,
      "delta": 0.9542999999999999,
      "delta_fmt": "+122.0%"
    },
    {
      "label": "7d Vol",
      "value": "8.48 ETH",
      "raw": 8.4813
    },
    {
      "label": "30d Vol",
      "value": "59.25 ETH",
      "raw": 59.2508
    },
    {
      "label": "Full Set Bid",
      "value": "43.8 ETH",
      "raw": 43.83
    },
    {
      "label": "Network TDH",
      "value": "1576.4M",
      "raw": 1576428256,
      "delta": 2370426,
      "delta_fmt": "+2.4M TDH"
    },
    {
      "label": "#1 6529er",
      "value": "92.9M TDH",
      "raw": 92901227,
      "delta": 12225598,
      "delta_fmt": "+12.2M TDH"
    },
    {
      "label": "#1 Strauss",
      "value": "61.2M TDH",
      "raw": 61232382,
      "delta": -378,
      "delta_fmt": "-0.0M TDH"
    },
    {
      "label": "#1 JamesAndrew",
      "value": "50.5M TDH",
      "raw": 50488368,
      "delta": 139,
      "delta_fmt": "+0.0M TDH"
    },
    {
      "label": "#1 Nrsin",
      "value": "62.6M TDH",
      "raw": 62583331,
      "delta": 34365,
      "delta_fmt": "+0.0M TDH"
    },
    {
      "label": "#1 jiwa",
      "value": "53.7M TDH",
      "raw": 53683835,
      "delta": 712953,
      "delta_fmt": "+0.7M TDH"
    },
    {
      "label": "Full Set",
      "value": "31",
      "raw": 31
    },
    {
      "label": "Holders",
      "value": "10,155",
      "raw": 10155
    }
  ],
  "headline_extras": [
    "PUNK6529: 108 MSGS IN THE LAST 24H IN MAYBE'S DIVE BAR",
    "DIVE BAR: 454 MSGS IN LAST 6H",
    "CARD #491: 126 MINTS (EXCL. MUSEUM) | 91 HOLDERS | JUST CULTURE",
    "ACTIVE TODAY: PUNK6529 (131 MSGS) | JAMESANDREW (77) | ZIGMARILLION (59)"
  ]
}