{
  "generated_at": "2026-05-15T00:11:44.719972+00:00",
  "model": "nvidia/nemotron-3-super-120b-a12b:free",
  "news": [
    {
      "category": "MINTING TODAY",
      "headline": "MINTING TODAY",
      "summary": "A new Meme Card is being minted today! \"WAGMI Ululation\" by Sherie_Margaret \u2014 68.2M TDH from 85 voters. Top supporter: gpebbles (14.1M TDH).",
      "source": "The Memes",
      "link": "https://6529.io/the-memes",
      "image": {
        "url": "https://d3lqz0a4bldqgf.cloudfront.net/drops/author_c8e0026e-b087-4350-86fb-24ea71d17d4f/fef0038e-d6ac-4f0a-bc1a-19e67d9a84cb/Wagmi-3.gif",
        "label": "WAGMI Ululation - Sherie_Margaret",
        "type": "image"
      },
      "dataBoxes": null
    },
    {
      "category": "TOP MEMES",
      "headline": "CasaNUA Leads with 63.4M Projected TDH",
      "summary": "\"6529 Memes at the Boys' Club\" by CasaNUA (63.4M projected TDH, 68 voters) | \"Network State of Mind\" by Zigmarillion (45.2M projected TDH, 100 voters) | \"The Meme Market\" by 1dontknows (29.0M projected TDH, 68 voters) Next selection: Fri May 15 at 17:00 CET.",
      "source": "The Memes - Main Stage",
      "link": "https://6529.io/waves/b6128077-ea78-4dd9-b381-52c4eadb2077",
      "image": {
        "url": "https://d3lqz0a4bldqgf.cloudfront.net/drops/author_0f8306a5-87b4-11ee-9d82-029a0e4b6159/186e691f-09f8-4a05-806f-891a1aa29185/6529-Memes-at-the-Boys-Club-Hugo-Faz-and-Pate-4K.mp4",
        "label": "6529 Memes at the Boys' Club - CasaNUA",
        "type": "video"
      },
      "dataBoxes": [
        {
          "label": "CasaNUA",
          "value": "63.4M",
          "sub": "proj. (68 votes)"
        },
        {
          "label": "Zigmarillion",
          "value": "45.2M",
          "sub": "proj. (100 votes)"
        },
        {
          "label": "1dontknows",
          "value": "29.0M",
          "sub": "proj. (68 votes)"
        }
      ]
    },
    {
      "category": "NEW MEMES SUBMISSIONS",
      "headline": "2 New Memes Submissions This Week",
      "summary": "2 submissions this week. Ranking: blocknoob (9.9M) | senemsad (4.8M).",
      "source": "Main Stage",
      "link": "https://6529.io/waves/b6128077-ea78-4dd9-b381-52c4eadb2077",
      "image": {
        "url": "https://d3lqz0a4bldqgf.cloudfront.net/drops/author_2b92399c-790c-4be9-90f8-efdd565d98fe/a66db279-7dcd-4890-9235-a79a516de934/LetThisMemeIn-4k.mp4",
        "label": "blocknoob (9.9M)",
        "type": "video"
      },
      "images": [
        {
          "url": "https://d3lqz0a4bldqgf.cloudfront.net/drops/author_2b92399c-790c-4be9-90f8-efdd565d98fe/a66db279-7dcd-4890-9235-a79a516de934/LetThisMemeIn-4k.mp4",
          "label": "blocknoob (9.9M)",
          "type": "video"
        },
        {
          "url": "https://d3lqz0a4bldqgf.cloudfront.net/drops/author_7f9896b7-ff52-4eec-bb5e-12a5e5bd3370/2219dcde-1349-4f53-87e5-6247f7bd996a/final.jpg",
          "label": "senemsad (4.8M)",
          "type": "image"
        }
      ],
      "dataBoxes": null
    },
    {
      "category": "TOP SUPERRARE",
      "headline": "#8 Bicasso \u2014 5K TDH",
      "summary": "JasonOPhoto (2.8M) | Articulate (2.2M) | Zigmarillion (1.2M) | Kostas_Photo (765K) | awhurst (555K) | blake69 (322K) | Gsen (149K) | Bicasso (5K)",
      "source": "SuperRare x 6529",
      "link": "https://6529.io/waves/d22e3046-a00e-48b9-b245-a339a44c37cd",
      "image": {
        "url": "https://d3lqz0a4bldqgf.cloudfront.net/drops/author_75d3eb13-6284-4a53-9711-a28949a29575/e8b2c91d-49e1-4639-ad81-252c29766042/IMG-1359.mp4",
        "label": "Bicasso (5K)",
        "type": "video"
      }
    },
    {
      "category": "SALES RECAP",
      "headline": "24 Sales Today - 1.12 ETH Volume",
      "summary": "24 sales in 24h for 1.12 ETH. Highest: \"AUTONOMY.EXE\" at 0.175 ETH.",
      "source": "OpenSea",
      "link": "https://opensea.io/collection/thememes6529",
      "image": {
        "url": "https://d3lqz0a4bldqgf.cloudfront.net/images/scaled_x450/0x33FD426905F149f8376e227d0C9D3340AaD17aF1/479.WEBP",
        "label": "AUTONOMY.EXE - 0.175 ETH",
        "type": "image"
      },
      "images": [
        {
          "url": "https://d3lqz0a4bldqgf.cloudfront.net/images/scaled_x450/0x33FD426905F149f8376e227d0C9D3340AaD17aF1/479.WEBP",
          "label": "AUTONOMY.EXE - 0.175 ETH",
          "type": "image"
        },
        {
          "url": "https://d3lqz0a4bldqgf.cloudfront.net/images/scaled_x450/0x33FD426905F149f8376e227d0C9D3340AaD17aF1/443.GIF",
          "label": "< no, really [ this ] is going to be our year > - 0.150 ETH",
          "type": "image"
        },
        {
          "url": "https://d3lqz0a4bldqgf.cloudfront.net/images/scaled_x450/0x33FD426905F149f8376e227d0C9D3340AaD17aF1/151.WEBP",
          "label": "BOOM - 0.071 ETH",
          "type": "image"
        }
      ],
      "dataBoxes": [
        {
          "label": "Sales 24h",
          "value": "24",
          "sub": ""
        },
        {
          "label": "Volume 24h",
          "value": "1.12",
          "sub": "ETH"
        },
        {
          "label": "Top Sale",
          "value": "0.175",
          "sub": "AUTONOMY.EXE"
        },
        {
          "label": "Floor",
          "value": "0.01697788",
          "sub": "ETH"
        }
      ]
    }
  ],
  "ticker": [
    {
      "label": "24h Vol",
      "value": "1.12 ETH",
      "raw": 1.124,
      "delta": 0.3370000000000001,
      "delta_fmt": "+42.8%"
    },
    {
      "label": "7d Vol",
      "value": "24.14 ETH",
      "raw": 24.1384
    },
    {
      "label": "30d Vol",
      "value": "70.05 ETH",
      "raw": 70.0499
    },
    {
      "label": "Full Set Bid",
      "value": "42.2 ETH",
      "raw": 42.18,
      "delta": 0.020000000000003126,
      "delta_fmt": "+0.02 ETH"
    },
    {
      "label": "Network TDH",
      "value": "1601.4M",
      "raw": 1601425448,
      "delta": 2480277,
      "delta_fmt": "+2.5M TDH"
    },
    {
      "label": "#1 CasaNUA",
      "value": "63.4M TDH",
      "raw": 63362529
    },
    {
      "label": "#1 Sherie_Margaret",
      "value": "68.2M TDH",
      "raw": 68217095,
      "delta": 318,
      "delta_fmt": "+0.0M TDH"
    },
    {
      "label": "#1 kristopher",
      "value": "70.2M TDH",
      "raw": 70164818,
      "delta": -19,
      "delta_fmt": "-0.0M TDH"
    },
    {
      "label": "#1 AEZY",
      "value": "57.4M TDH",
      "raw": 57404678
    },
    {
      "label": "#1 6529er",
      "value": "132.5M TDH",
      "raw": 132542922,
      "delta": 7782,
      "delta_fmt": "+0.0M TDH"
    },
    {
      "label": "#1 Strauss",
      "value": "61.2M TDH",
      "raw": 61232382,
      "delta": -378,
      "delta_fmt": "-0.0M TDH"
    },
    {
      "label": "#1 JamesAndrew",
      "value": "50.5M TDH",
      "raw": 50488368,
      "delta": 139,
      "delta_fmt": "+0.0M TDH"
    },
    {
      "label": "#1 Nrsin",
      "value": "62.6M TDH",
      "raw": 62583331,
      "delta": 34365,
      "delta_fmt": "+0.0M TDH"
    },
    {
      "label": "#1 jiwa",
      "value": "53.7M TDH",
      "raw": 53683835,
      "delta": 712953,
      "delta_fmt": "+0.7M TDH"
    },
    {
      "label": "Full Set",
      "value": "31",
      "raw": 31
    },
    {
      "label": "Holders",
      "value": "10,155",
      "raw": 10155
    }
  ],
  "headline_extras": [
    "PUNK6529 LAST SEEN: maybe's dive bar (May 10)",
    "CARD #495: 148 MINTS (EXCL. MUSEUM) | 101 HOLDERS | PERMISSIONLESS CROSSING",
    "ACTIVE TODAY: SHERIE_MARGARET (86 MSGS) | JASONOPHOTO (74) | GRAFFITIONGRAVE (73)",
    "DIVE BAR: 256 MSGS IN LAST 6H"
  ]
}